Metadata-Version: 2.4
Name: picsellia-sam2
Version: 0.1.0
Summary: Picsellia fork of Meta's SAM 2
Home-page: https://github.com/facebookresearch/sam2
Author: Meta AI
Author-email: Pierre-Nicolas Tiffreau <pierre-nicolas@picsellia.com>
License: MIT
Keywords: foo,bar
Classifier: Programming Language :: Python :: 3
Classifier: License :: OSI Approved :: MIT License
Classifier: Operating System :: OS Independent
Requires-Python: >=3.10.0
License-File: LICENSE
License-File: LICENSE_cctorch
Dynamic: author
Dynamic: home-page
Dynamic: license-file
Dynamic: requires-python
